LICENSE
README.md
setup.py
satclave/__init__.py
satclave/graph.py
satclave/vector.py
satclave.egg-info/PKG-INFO
satclave.egg-info/SOURCES.txt
satclave.egg-info/dependency_links.txt
satclave.egg-info/top_level.txt