Metadata-Version: 2.1
Name: satclave
Version: 0.1.2
Summary: A library with computational and mathematical functions!
Home-page: https://satclave.readthedocs.io/
Author: Aitzaz Imtiaz
Author-email: aitzazimtiaz855@gmail.com
License: MIT
Classifier: Intended Audience :: Developers
Classifier: License :: OSI Approved :: MIT License
Classifier: Programming Language :: Python
Classifier: Programming Language :: Python :: 3
Classifier: Programming Language :: Python :: 3.6
Classifier: Programming Language :: Python :: 3.7
Classifier: Programming Language :: Python :: 3.8
Classifier: Programming Language :: Python :: 3.9
Classifier: Operating System :: OS Independent
License-File: LICENSE
